[
    {
        "id": "tt31193180",
        "url": "https://www.imdb.com/title/tt31193180/",
        "primaryTitle": "Sinners",
        "originalTitle": "Sinners",
        "type": "movie",
        "description": "Trying to leave their troubled lives behind, twin brothers return to their hometown to start again, only to discover that an even greater evil is waiting to welcome them back.",
        "primaryImage": "https://m.media-amazon.com/images/M/MV5BNjIwZWY4ZDEtMmIxZS00NDA4LTg4ZGMtMzUwZTYyNzgxMzk5XkEyXkFqcGc@._V1_.jpg",
        "trailer": "https://www.youtube.com/watch?v=bKGxHflevuk",
        "contentRating": "R",
        "startYear": 2025,
        "endYear": null,
        "releaseDate": "2025-04-18",
        "interests": [
            "Period Drama",
            "Supernatural Horror",
            "Vampire Horror",
            "Action",
            "Drama",
            "Horror",
            "Thriller"
        ],
        "countriesOfOrigin": [
            "US"
        ],
        "externalLinks": [
            "https://amzn.to/4cNibD5",
            "https://www.sinnersmovie.com/"
        ],
        "spokenLanguages": [
            "en"
        ],
        "filmingLocations": [
            "New Orleans, Louisiana, USA"
        ],
        "productionCompanies": [
            {
                "id": "co0002663",
                "name": "Warner Bros."
            },
            {
                "id": "co1090055",
                "name": "Domain Entertainment (II)"
            },
            {
                "id": "co0843639",
                "name": "Proximity Media"
            }
        ],
        "budget": 90000000,
        "grossWorldwide": 63507468,
        "genres": [
            "Action",
            "Drama",
            "Horror"
        ],
        "isAdult": false,
        "runtimeMinutes": 137,
        "averageRating": 8.2,
        "numVotes": 25803,
        "metascore": 84
    },
    {
        "id": "tt3566834",
        "url": "https://www.imdb.com/title/tt3566834/",
        "primaryTitle": "A Minecraft Movie",
        "originalTitle": "A Minecraft Movie",
        "type": "movie",
        "description": "Four misfits are suddenly pulled through a mysterious portal into a bizarre cubic wonderland that thrives on imagination. To get back home they'll have to master this world while embarking on a quest with an unexpected expert crafter.",
        "primaryImage": "https://m.media-amazon.com/images/M/MV5BYzFjMzNjOTktNDBlNy00YWZhLWExYTctZDcxNDA4OWVhOTJjXkEyXkFqcGc@._V1_.jpg",
        "trailer": "https://www.youtube.com/watch?v=wJO_vIDZn-I",
        "contentRating": "PG",
        "startYear": 2025,
        "endYear": null,
        "releaseDate": "2025-04-04",
        "interests": [
            "Action Epic",
            "Adventure Epic",
            "Fantasy Epic",
            "High-Concept Comedy",
            "Quest",
            "Slapstick",
            "Survival",
            "Action",
            "Adventure",
            "Comedy"
        ],
        "countriesOfOrigin": [
            "SE",
            "US",
            "NZ",
            "CA"
        ],
        "externalLinks": [
            "https://www.minecraft-movie.com/home/",
            "https://www.youtube.com/watch?v=EaOnM8SewHc&ab"
        ],
        "spokenLanguages": [
            "en"
        ],
        "filmingLocations": [
            "Auckland, New Zealand"
        ],
        "productionCompanies": [
            {
                "id": "co0002663",
                "name": "Warner Bros."
            },
            {
                "id": "co0159111",
                "name": "Legendary Entertainment"
            },
            {
                "id": "co0084207",
                "name": "Vertigo Entertainment"
            }
        ],
        "budget": 150000000,
        "grossWorldwide": 717824380,
        "genres": [
            "Action",
            "Adventure",
            "Comedy"
        ],
        "isAdult": false,
        "runtimeMinutes": 101,
        "averageRating": 5.9,
        "numVotes": 67786,
        "metascore": 45
    },
    {
        "id": "tt6208148",
        "url": "https://www.imdb.com/title/tt6208148/",
        "primaryTitle": "Snow White",
        "originalTitle": "Snow White",
        "type": "movie",
        "description": "A princess joins forces with seven dwarfs and a group of rebels to liberate her kingdom from her cruel stepmother the Evil Queen.",
        "primaryImage": "https://m.media-amazon.com/images/M/MV5BY2UwOGUxMzEtMzEyZi00NjEwLTkxOTMtYTljOWEzYjYyMWNjXkEyXkFqcGc@._V1_.jpg",
        "trailer": "https://www.youtube.com/watch?v=iV46TJKL8cU",
        "contentRating": "PG",
        "startYear": 2025,
        "endYear": null,
        "releaseDate": "2025-03-21",
        "interests": [
            "Fairy Tale",
            "Feel-Good Romance",
            "Adventure",
            "Family",
            "Fantasy",
            "Musical",
            "Romance"
        ],
        "countriesOfOrigin": [
            "US"
        ],
        "externalLinks": [
            "https://www.facebook.com/DisneySnowWhite/",
            "https://movies.disney.com/snow-white-2025"
        ],
        "spokenLanguages": [
            "en",
            "de"
        ],
        "filmingLocations": [
            "Pinewood Studios, Iver Heath, Buckinghamshire, England, UK"
        ],
        "productionCompanies": [
            {
                "id": "co0008970",
                "name": "Walt Disney Pictures"
            },
            {
                "id": "co0093810",
                "name": "Marc Platt Productions"
            }
        ],
        "budget": 250000000,
        "grossWorldwide": 194099875,
        "genres": [
            "Adventure",
            "Family",
            "Fantasy"
        ],
        "isAdult": false,
        "runtimeMinutes": 109,
        "averageRating": 1.6,
        "numVotes": 343330,
        "metascore": 50
    },
    {
        "id": "tt31434639",
        "url": "https://www.imdb.com/title/tt31434639/",
        "primaryTitle": "Warfare",
        "originalTitle": "Warfare",
        "type": "movie",
        "description": "A platoon of Navy SEALs embark on a dangerous mission in Ramadi, Iraq, with the chaos and brotherhood of war retold through their memories of the event.",
        "primaryImage": "https://m.media-amazon.com/images/M/MV5BYzEyYjE1NmEtOTFmNy00ZmQxLThlYzctOGRjNmQ0N2VjMmNmXkEyXkFqcGc@._V1_.jpg",
        "trailer": "https://www.youtube.com/watch?v=JER0Fkyy3tw",
        "contentRating": "R",
        "startYear": 2025,
        "endYear": null,
        "releaseDate": "2025-04-11",
        "interests": [
            "Docudrama",
            "War Epic",
            "Action",
            "Drama",
            "War"
        ],
        "countriesOfOrigin": [
            "US",
            "GB"
        ],
        "externalLinks": [
            "https://a24films.com/films/warfare"
        ],
        "spokenLanguages": [
            "en"
        ],
        "filmingLocations": [
            "Iraq"
        ],
        "productionCompanies": [
            {
                "id": "co0390816",
                "name": "A24"
            },
            {
                "id": "co0103974",
                "name": "DNA Films"
            }
        ],
        "budget": 20000000,
        "grossWorldwide": 17273806,
        "genres": [
            "Action",
            "Drama",
            "War"
        ],
        "isAdult": false,
        "runtimeMinutes": 95,
        "averageRating": 7.9,
        "numVotes": 10523,
        "metascore": 78
    },
    {
        "id": "tt0899043",
        "url": "https://www.imdb.com/title/tt0899043/",
        "primaryTitle": "The Amateur",
        "originalTitle": "The Amateur",
        "type": "movie",
        "description": "When his supervisors at the CIA refuse to take action after his wife is killed in a London terrorist attack, a decoder takes matters into his own hands.",
        "primaryImage": "https://m.media-amazon.com/images/M/MV5BYjhkZjM3ZWYtMjUxMS00YzhlLTkxZWYtMzhkMzFhOTQ1NjRkXkEyXkFqcGc@._V1_.jpg",
        "trailer": "https://www.youtube.com/watch?v=DCWcK4c-F8Q",
        "contentRating": "PG-13",
        "startYear": 2025,
        "endYear": null,
        "releaseDate": "2025-04-11",
        "interests": [
            "Spy",
            "Action",
            "Thriller"
        ],
        "countriesOfOrigin": [
            "US"
        ],
        "externalLinks": [
            "https://www.20thcenturystudios.com.au/movies/the-amateur",
            "https://www.20thcenturystudios.com/movies/the-amateur"
        ],
        "spokenLanguages": [
            "en"
        ],
        "filmingLocations": [
            "Turkey"
        ],
        "productionCompanies": [
            {
                "id": "co0781821",
                "name": "20th Century Studios"
            },
            {
                "id": "co0381873",
                "name": "Hutch Parker Entertainment"
            },
            {
                "id": "co0701714",
                "name": "Joel B. Michaels Productions"
            }
        ],
        "budget": 60000000,
        "grossWorldwide": 63834080,
        "genres": [
            "Action",
            "Thriller"
        ],
        "isAdult": false,
        "runtimeMinutes": 122,
        "averageRating": 6.7,
        "numVotes": 12827,
        "metascore": 52
    },
    {
        "id": "tt23476986",
        "url": "https://www.imdb.com/title/tt23476986/",
        "primaryTitle": "G20",
        "originalTitle": "G20",
        "type": "movie",
        "description": "Terrorists take over the G20 summit with President Sutton, bringing her governing and military experience to defend her family, company, and the world.",
        "primaryImage": "https://m.media-amazon.com/images/M/MV5BMTc5MTg3MTEtNzQwMi00Y2VkLWI4N2UtNDdmMzFjMGIyNTEzXkEyXkFqcGc@._V1_.jpg",
        "trailer": "https://www.youtube.com/watch?v=mhQcpvKHis4",
        "contentRating": "R",
        "startYear": 2025,
        "endYear": null,
        "releaseDate": "2025-04-10",
        "interests": [
            "Action",
            "Thriller"
        ],
        "countriesOfOrigin": [
            "US"
        ],
        "externalLinks": [
            "https://press.amazonmgmstudios.com/us/en/original-movies/g20"
        ],
        "spokenLanguages": [
            "en"
        ],
        "filmingLocations": [
            "Cape Town, South Africa"
        ],
        "productionCompanies": [
            {
                "id": "co0319272",
                "name": "Amazon Studios"
            },
            {
                "id": "co0203259",
                "name": "Big Indie Pictures"
            },
            {
                "id": "co0373915",
                "name": "JuVee Productions"
            }
        ],
        "budget": null,
        "grossWorldwide": null,
        "genres": [
            "Action",
            "Thriller"
        ],
        "isAdult": false,
        "runtimeMinutes": 108,
        "averageRating": 5.1,
        "numVotes": 15300,
        "metascore": 53
    },
    {
        "id": "tt10676052",
        "url": "https://www.imdb.com/title/tt10676052/",
        "primaryTitle": "The Fantastic Four: First Steps",
        "originalTitle": "The Fantastic Four: First Steps",
        "type": "movie",
        "description": "Forced to balance their roles as heroes with the strength of their family bond, the Fantastic Four must defend Earth from a ravenous space god called Galactus and his enigmatic Herald, Silver Surfer.",
        "primaryImage": "https://m.media-amazon.com/images/M/MV5BY2U5MjM2MWEtYTU2ZC00YjkyLWE2ZTctYzI1ZDI3Y2IzNGVkXkEyXkFqcGc@._V1_.jpg",
        "trailer": null,
        "contentRating": null,
        "startYear": 2025,
        "endYear": null,
        "releaseDate": "2025-07-25",
        "interests": [
            "Space Sci-Fi",
            "Superhero",
            "Action",
            "Adventure",
            "Sci-Fi"
        ],
        "countriesOfOrigin": [
            "US"
        ],
        "externalLinks": [
            "https://www.facebook.com/FantasticFour"
        ],
        "spokenLanguages": [
            "en"
        ],
        "filmingLocations": [
            "London, England, UK"
        ],
        "productionCompanies": [
            {
                "id": "co0051941",
                "name": "Marvel Studios"
            },
            {
                "id": "co0781821",
                "name": "20th Century Studios"
            }
        ],
        "budget": null,
        "grossWorldwide": null,
        "genres": [
            "Action",
            "Adventure",
            "Sci-Fi"
        ],
        "isAdult": false,
        "runtimeMinutes": null,
        "averageRating": null,
        "numVotes": null,
        "metascore": null
    },
    {
        "id": "tt9150192",
        "url": "https://www.imdb.com/title/tt9150192/",
        "primaryTitle": "A Working Man",
        "originalTitle": "A Working Man",
        "type": "movie",
        "description": "Levon Cade left his profession behind to work construction and be a good dad to his daughter. But when a local girl vanishes, he's asked to return to the skills that made him a mythic figure in the shadowy world of counter-terrorism.",
        "primaryImage": "https://m.media-amazon.com/images/M/MV5BYmQxZGIxNTYtYTQwMy00ODdkLWI0MmQtM2E0ZmIyNmYzMGMzXkEyXkFqcGc@._V1_.jpg",
        "trailer": "https://www.youtube.com/watch?v=zTbgNC42Ops",
        "contentRating": "R",
        "startYear": 2025,
        "endYear": null,
        "releaseDate": "2025-03-28",
        "interests": [
            "Conspiracy Thriller",
            "One-Person Army Action",
            "Action",
            "Thriller"
        ],
        "countriesOfOrigin": [
            "GB",
            "US"
        ],
        "externalLinks": [
            "https://www.instagram.com/balboa_productions/",
            "https://www.instagram.com/aworkingmanmovie/"
        ],
        "spokenLanguages": [
            "en",
            "ru",
            "es"
        ],
        "filmingLocations": [
            "London, England, UK"
        ],
        "productionCompanies": [
            {
                "id": "co1025982",
                "name": "Amazon MGM Studios"
            },
            {
                "id": "co1031934",
                "name": "Black Bear"
            },
            {
                "id": "co0255750",
                "name": "Block Films"
            }
        ],
        "budget": 40000000,
        "grossWorldwide": 86925155,
        "genres": [
            "Action",
            "Thriller"
        ],
        "isAdult": false,
        "runtimeMinutes": 116,
        "averageRating": 5.8,
        "numVotes": 21620,
        "metascore": 52
    },
    {
        "id": "tt12299608",
        "url": "https://www.imdb.com/title/tt12299608/",
        "primaryTitle": "Mickey 17",
        "originalTitle": "Mickey 17",
        "type": "movie",
        "description": "During a human expedition to colonize space, Mickey 17, a so-called \"expendable\" employee, is sent to explore an ice planet.",
        "primaryImage": "https://m.media-amazon.com/images/M/MV5BZGQwYmEzMzktYzBmMy00NmVmLTkyYTUtOTYyZjliZDNhZGVkXkEyXkFqcGc@._V1_.jpg",
        "trailer": "https://www.youtube.com/watch?v=osYpGSz_0i4",
        "contentRating": "R",
        "startYear": 2025,
        "endYear": null,
        "releaseDate": "2025-03-07",
        "interests": [
            "Alien Invasion",
            "Dark Comedy",
            "Space Sci-Fi",
            "Adventure",
            "Comedy",
            "Fantasy",
            "Sci-Fi"
        ],
        "countriesOfOrigin": [
            "US",
            "KR"
        ],
        "externalLinks": [
            "https://www.mickey17movie.com/home/"
        ],
        "spokenLanguages": [
            "en"
        ],
        "filmingLocations": [
            "Warner Bros. Studios Leavesden, Warner Drive, Leavesden, Watford, Hertfordshire, England, UK"
        ],
        "productionCompanies": [
            {
                "id": "co0002663",
                "name": "Warner Bros."
            },
            {
                "id": "co0136967",
                "name": "Plan B Entertainment"
            },
            {
                "id": "co1091406",
                "name": "Offscreen"
            }
        ],
        "budget": 118000000,
        "grossWorldwide": 131802053,
        "genres": [
            "Adventure",
            "Comedy",
            "Fantasy"
        ],
        "isAdult": false,
        "runtimeMinutes": 137,
        "averageRating": 6.9,
        "numVotes": 102980,
        "metascore": 72
    },
    {
        "id": "tt32149847",
        "url": "https://www.imdb.com/title/tt32149847/",
        "primaryTitle": "Drop",
        "originalTitle": "Drop",
        "type": "movie",
        "description": "A widowed mother's first date in years takes a terrifying turn when she's bombarded with anonymous threatening messages on her phone during their upscale dinner, leaving her questioning if her charming date is behind the harassment.",
        "primaryImage": "https://m.media-amazon.com/images/M/MV5BOWUyOTNlMjItNWUyZC00ZGJiLTg3MDMtODJmMGQyMGY3NzU3XkEyXkFqcGc@._V1_.jpg",
        "trailer": "https://www.youtube.com/watch?v=bs_nFwh5eJw",
        "contentRating": "PG-13",
        "startYear": 2025,
        "endYear": null,
        "releaseDate": "2025-04-11",
        "interests": [
            "Whodunnit",
            "Drama",
            "Mystery",
            "Thriller"
        ],
        "countriesOfOrigin": [
            "US",
            "IE"
        ],
        "externalLinks": [
            "https://amzn.to/42FMOH8",
            "https://www.facebook.com/DropTheMovie/"
        ],
        "spokenLanguages": [
            "en"
        ],
        "filmingLocations": [
            "Ardmore Studios, Bray, County Wicklow, Ireland"
        ],
        "productionCompanies": [
            {
                "id": "co0098315",
                "name": "Blumhouse Productions"
            },
            {
                "id": "co0071240",
                "name": "Platinum Dunes"
            },
            {
                "id": "co0725291",
                "name": "Wild Atlantic Pictures"
            }
        ],
        "budget": 11000000,
        "grossWorldwide": 20563235,
        "genres": [
            "Drama",
            "Mystery",
            "Thriller"
        ],
        "isAdult": false,
        "runtimeMinutes": 95,
        "averageRating": 6.5,
        "numVotes": 6527,
        "metascore": 65
    }
]